pyrevolut/__init__.py
pyrevolut/api/__init__.py
pyrevolut/api/accounts/__init__.py
pyrevolut/api/accounts/endpoint/__init__.py
pyrevolut/api/accounts/endpoint/asynchronous.py
pyrevolut/api/accounts/endpoint/synchronous.py
pyrevolut/api/accounts/get/__init__.py
pyrevolut/api/accounts/get/retrieve_all_accounts.py
pyrevolut/api/accounts/get/retrieve_an_account.py
pyrevolut/api/accounts/get/retrieve_full_bank_details.py
pyrevolut/api/accounts/resources/__init__.py
pyrevolut/api/accounts/resources/account.py
pyrevolut/api/cards/__init__.py
pyrevolut/api/cards/delete/__init__.py
pyrevolut/api/cards/delete/terminate_card.py
pyrevolut/api/cards/endpoint/__init__.py
pyrevolut/api/cards/endpoint/asynchronous.py
pyrevolut/api/cards/endpoint/synchronous.py
pyrevolut/api/cards/get/__init__.py
pyrevolut/api/cards/get/retrieve_card_details.py
pyrevolut/api/cards/get/retrieve_list_of_cards.py
pyrevolut/api/cards/get/retrieve_sensitive_card_details.py
pyrevolut/api/cards/patch/__init__.py
pyrevolut/api/cards/patch/update_card_details.py
pyrevolut/api/cards/post/__init__.py
pyrevolut/api/cards/post/create_card.py
pyrevolut/api/cards/post/freeze_card.py
pyrevolut/api/cards/post/unfreeze_card.py
pyrevolut/api/cards/resources/__init__.py
pyrevolut/api/cards/resources/card.py
pyrevolut/api/common/__init__.py
pyrevolut/api/common/endpoint.py
pyrevolut/api/common/enums/__init__.py
pyrevolut/api/common/enums/account_name_match_code.py
pyrevolut/api/common/enums/account_name_match_reason_code.py
pyrevolut/api/common/enums/account_name_match_reason_type.py
pyrevolut/api/common/enums/account_state.py
pyrevolut/api/common/enums/account_type.py
pyrevolut/api/common/enums/card_scheme.py
pyrevolut/api/common/enums/card_state.py
pyrevolut/api/common/enums/charge_bearer.py
pyrevolut/api/common/enums/merchant_category.py
pyrevolut/api/common/enums/payment_draft_state.py
pyrevolut/api/common/enums/payment_scheme.py
pyrevolut/api/common/enums/payout_link_cancellation_reason.py
pyrevolut-0.9.1.dist-info/LICENSE
pyrevolut-0.9.1.dist-info/METADATA
pyrevolut-0.9.1.dist-info/WHEEL
pyrevolut-0.9.1.dist-info/entry_points.txt
pyrevolut-0.9.1.dist-info/RECORD
