Metadata-Version: 2.1
Name: pyrevolut
Version: 0.9.1
Summary: An unofficial Python API Wrapper for the Revolut Business API
Home-page: https://github.com/Trevypants/pyrevolut
License: MIT
Author: Trevor Visser
Author-email: trevor.visser@gmail.com
Requires-Python: >=3.11,<4.0
Classifier: License :: OSI Approved :: MIT License
Classifier: Programming Language :: Python :: 3
Classifier: Programming Language :: Python :: 3.11
Classifier: Programming Language :: Python :: 3.12
Requires-Dist: authlib (==1.*)
Requires-Dist: cryptography (==42.*)
Requires-Dist: httpx (==0.*)
Requires-Dist: pendulum (==3.*)
Requires-Dist: phonenumbers (==8.*)
Requires-Dist: pycountry (==23.*)
Requires-Dist: pydantic-extra-types (==2.*)
Requires-Dist: pydantic[email] (==2.*)
Requires-Dist: pyjwt[crypto] (==2.*)
Requires-Dist: typer (==0.*)
